odbp/__init__.py
odbp/__main__.py
odbp/cli.py
odbp/magic.py
odbp/odb.py
odbp/odb_settings.py
odbp/process_input.py
odbp/reader.py
odbp/types.py
odbp/writer.py
odbp/data/config.toml
odbp/data/views.toml
odbp/py2_scripts/converter.py
odbp/py2_scripts/extractor.py
odbp/py2_scripts/odb_info_getter.py
odb_plotter-1.0.2.dist-info/LICENSE
odb_plotter-1.0.2.dist-info/METADATA
odb_plotter-1.0.2.dist-info/WHEEL
odb_plotter-1.0.2.dist-info/top_level.txt
odb_plotter-1.0.2.dist-info/RECORD
