Metadata-Version: 2.1
Name: odb-plotter
Version: 1.0.2
Summary: Python3 API for Abaqus .odb Files and related Command Line Visualization Tool. Focused on Additive Manufacturing Thermal Transfer
Author-email: Clark Hensley <clarkhensley@duck.com>
Maintainer-email: Clark Hensley <clarkhensley@duck.com>
License: MIT License
Project-URL: Homepage, https://www.cmml.me.msstate.edu
Project-URL: Bug Reports, https://www.github.com/Computational-Mechanics-Materials-Lab/ODBPlotter/issues
Project-URL: Source, https://www.github.com/Computational-Mechanics-Materials-Lab/ODBPlotter
Keywords: abaqus,abq,fea,odb,waam,wa-ded,visualization
License-File: LICENSE
Requires-Dist: platformdirs
Requires-Dist: h5py
Requires-Dist: numpy
Requires-Dist: tomli-w
Requires-Dist: pandas
Requires-Dist: pyvista
Requires-Dist: pyreadline3 ; platform_system == "Windows"
Requires-Dist: tomli >=1.1.0 ; python_version < "3.11"
